LICENSE.txt
MANIFEST.in
README.md
setup.py
lcopt_cv/__init__.py
lcopt_cv/grab_flow_chart.py
lcopt_cv/gui.py
lcopt_cv/heuristics.py
lcopt_cv/send_to_lcopt.py
lcopt_cv.egg-info/PKG-INFO
lcopt_cv.egg-info/SOURCES.txt
lcopt_cv.egg-info/dependency_links.txt
lcopt_cv.egg-info/entry_points.txt
lcopt_cv.egg-info/requires.txt
lcopt_cv.egg-info/top_level.txt
lcopt_cv/assets/icon.ico
lcopt_cv/assets/icon.png
lcopt_cv/assets/icon1.png
lcopt_cv/assets/locations.json
lcopt_cv/bin/lcopt_cv_gui.py
lcopt_cv/bin/lcopt_cv_gui_q.pyw
lcopt_cv/bin/__pycache__/lcopt_cv_gui.cpython-36.pyc
lcopt_cv/bin/__pycache__/lcopt_cv_gui_q.cpython-36.pyc