Metadata-Version: 1.1
Name: lcopt-cv
Version: 0.1.3
Summary: Computer vision module that links to lcopt
Home-page: https://github.com/pjamesjoyce/lcopt_cv/
Author: P. James Joyce
Author-email: pjamesjoyce@gmail.com
License: BSD 3-Clause License
